karrio/mappers/royalmail/__init__.py
karrio/mappers/royalmail/mapper.py
karrio/mappers/royalmail/proxy.py
karrio/mappers/royalmail/settings.py
karrio/plugins/royalmail/__init__.py
karrio/providers/royalmail/__init__.py
karrio/providers/royalmail/error.py
karrio/providers/royalmail/tracking.py
karrio/providers/royalmail/units.py
karrio/providers/royalmail/utils.py
karrio/schemas/royalmail/__init__.py
karrio/schemas/royalmail/errors.py
karrio/schemas/royalmail/tracking.py
karrio_royalmail-2026.1.4.dist-info/METADATA
karrio_royalmail-2026.1.4.dist-info/WHEEL
karrio_royalmail-2026.1.4.dist-info/entry_points.txt
karrio_royalmail-2026.1.4.dist-info/top_level.txt
karrio_royalmail-2026.1.4.dist-info/RECORD
